README.rst
setup.py
tox_run_before.py
tox_run_before.egg-info/PKG-INFO
tox_run_before.egg-info/SOURCES.txt
tox_run_before.egg-info/dependency_links.txt
tox_run_before.egg-info/entry_points.txt
tox_run_before.egg-info/not-zip-safe
tox_run_before.egg-info/requires.txt
tox_run_before.egg-info/top_level.txt