Metadata-Version: 1.1
Name: tox-run-before
Version: 0.1
Summary: Tox plugin to run shell commands before the test environments are created.
Home-page: UNKNOWN
Author: Praekelt Consulting
Author-email: dev@praekelt.com
License: BSD
Platform: UNKNOWN
Classifier: Programming Language :: Python
Classifier: License :: OSI Approved :: BSD License
Classifier: Operating System :: OS Independent
Classifier: Intended Audience :: Developers
Classifier: Topic :: Internet :: WWW/HTTP :: Dynamic Content
